ftpdol/__init__.py
ftpdol-0.0.4.dist-info/LICENSE
ftpdol-0.0.4.dist-info/METADATA
ftpdol-0.0.4.dist-info/WHEEL
ftpdol-0.0.4.dist-info/top_level.txt
ftpdol-0.0.4.dist-info/RECORD
