Metadata-Version: 2.1
Name: ftpdol
Version: 0.0.4
Summary: ftp with a simple (dict-like or list-like) interface
Home-page: https://github.com/i2mint/ftpdol
Author: OtoSense
License: apache-2.0
Keywords: ftp
Platform: any
Requires-Dist: dol
